examples/__init__.py
examples/cifar_simple/__init__.py
examples/cifar_simple/experiment.py
examples/cifar_simple/model.py
examples/digit-recognizer/__init__.py
examples/digit-recognizer/dataset.py
examples/digit-recognizer/experiment.py
examples/digit-recognizer/model.py
examples/digit-recognizer/executors/__init__.py
examples/digit-recognizer/executors/infer.py
examples/digit-recognizer/executors/valid.py
mlcomp/__init__.py
mlcomp/__main__.py
mlcomp/__version__.py
mlcomp/report.py
mlcomp/bin/redis-License.md
mlcomp/bin/redis-server
mlcomp/contrib/__init__.py
mlcomp/contrib/__main__.py
mlcomp/contrib/catalyst/__init__.py
mlcomp/contrib/catalyst/register.py
mlcomp/contrib/catalyst/callbacks/__init__.py
mlcomp/contrib/catalyst/callbacks/inference.py
mlcomp/contrib/catalyst/optim/__init__.py
mlcomp/contrib/catalyst/optim/cosineanneal.py
mlcomp/contrib/complex/__init__.py
mlcomp/contrib/complex/infer.py
mlcomp/contrib/criterion/__init__.py
mlcomp/contrib/criterion/ce.py
mlcomp/contrib/criterion/ring.py
mlcomp/contrib/criterion/triplet.py
mlcomp/contrib/dataset/__init__.py
mlcomp/contrib/dataset/classify.py
mlcomp/contrib/dataset/segment.py
mlcomp/contrib/dataset/video.py
mlcomp/contrib/metrics/__init__.py
mlcomp/contrib/metrics/dice.py
mlcomp/contrib/model/__init__.py
mlcomp/contrib/model/efficientnet.py
mlcomp/contrib/model/pretrained.py
mlcomp/contrib/model/segmentation_model_pytorch.py
mlcomp/contrib/model/timm.py
mlcomp/contrib/model/video/__init__.py
mlcomp/contrib/model/video/resnext3d/__init__.py
mlcomp/contrib/model/video/resnext3d/r2plus1_util.py
mlcomp/contrib/model/video/resnext3d/resnext3d.py
mlcomp/contrib/model/video/resnext3d/resnext3d_block.py
mlcomp/contrib/model/video/resnext3d/resnext3d_stage.py
mlcomp/contrib/model/video/resnext3d/resnext3d_stem.py
mlcomp/contrib/sampler/__init__.py
mlcomp/contrib/sampler/balanced.py
mlcomp/contrib/sampler/distributed.py
mlcomp/contrib/sampler/hard_negative.py
mlcomp/contrib/scripts/__init__.py
mlcomp-20.3.1.dist-info/LICENSE
mlcomp-20.3.1.dist-info/METADATA
mlcomp-20.3.1.dist-info/WHEEL
mlcomp-20.3.1.dist-info/entry_points.txt
mlcomp-20.3.1.dist-info/top_level.txt
mlcomp-20.3.1.dist-info/RECORD
