Metadata-Version: 2.1
Name: mlcomp
Version: 20.3.1
Summary: Machine learning pipelines. Especially, for competitions, like Kaggle
Home-page: https://github.com/catalyst-team/mlcomp
Author: Evgeny Semyonov
Author-email: lightsanweb@gmail.com
License: MIT
Platform: UNKNOWN
Classifier: License :: OSI Approved :: MIT License
Classifier: Intended Audience :: Developers
Classifier: Intended Audience :: Science/Research
Classifier: Programming Language :: Python
Classifier: Programming Language :: Python :: 3.6
Classifier: Programming Language :: Python :: 3.7
Classifier: Programming Language :: Python :: Implementation :: CPython
Classifier: Topic :: Scientific/Engineering :: Artificial Intelligence
Requires-Python: >=3.6.0
Requires-Dist: Pillow (<7)
Requires-Dist: PyYAML (>=5.1)
Requires-Dist: redis
Requires-Dist: setuptools (>=41.0.1)
Requires-Dist: click (>=7.0)
Requires-Dist: psutil (>=5.6.2)
Requires-Dist: GPUtil (==1.4.0)
Requires-Dist: pathspec (>=0.5.9)
Requires-Dist: apscheduler (>=3.6.0)
Requires-Dist: sqlalchemy (>=1.3.4)
Requires-Dist: celery (>=4.3.0)
Requires-Dist: kaggle (>=1.5.3)
Requires-Dist: scipy (>=1.3.0)
Requires-Dist: flask (>=1.0.2)
Requires-Dist: requests
Requires-Dist: flask-cors (>=3.0.6)
Requires-Dist: sqlalchemy-serializer (==1.3.1)
Requires-Dist: scikit-learn (>=0.21.2)
Requires-Dist: psycopg2-binary (>=2.8.2)
Requires-Dist: tiffile
Requires-Dist: albumentations (>=0.2.3)
Requires-Dist: sqlalchemy-migrate (>=0.12.0)
Requires-Dist: cython
Requires-Dist: supervisor (>=4.0.4)
Requires-Dist: torchvision (>=0.4.2)
Requires-Dist: torch (>=1.0.0)
Requires-Dist: numpy (>=1.18.0)
Requires-Dist: pandas (>=0.25.3)
Requires-Dist: tqdm (>=4.39.0)
Requires-Dist: simplejson (>=3.13.2)
Requires-Dist: jupyter
Requires-Dist: networkx (>=2.2)
Requires-Dist: pytest (>=5.0.1)
Requires-Dist: pytest-xdist (>=1.29.0)
Requires-Dist: pretrainedmodels (>=0.7.4)
Requires-Dist: catalyst (==20.3.1)
